setup.py
magnet/__init__.py
magnet/magnet_url.py
magnetpy.egg-info/PKG-INFO
magnetpy.egg-info/SOURCES.txt
magnetpy.egg-info/dependency_links.txt
magnetpy.egg-info/top_level.txt