Metadata-Version: 1.0
Name: magnetpy
Version: 0.0.1
Summary: very simple and half-assed magnet url parser written in python.
Home-page: https://github.com/jarekps/magnetpy
Author: JarekPS
Author-email: jot@smiejczak.net
License: New BSD License
Keywords: magnet bittorent urlparser url torrent
Platform: UNKNOWN
